{"config":{"output_file":null,"full_docs":false,"pub_only":true,"reachable_only":true,"distro_crate":false,"signatures":false,"borrow_data":false},"version":"0.19.0","compilation":{"directory":"/home/iamkhalifaMBA/.cargo/registry/src/github.com-1ecc6299db9ec823/hash256-std-hasher-0.15.2","program":"/home/iamkhalifaMBA/.rustup/toolchains/nightly-2020-11-16-x86_64-unknown-linux-gnu/bin/rls","arguments":["--crate-name","hash256_std_hasher","/home/iamkhalifaMBA/.cargo/registry/src/github.com-1ecc6299db9ec823/hash256-std-hasher-0.15.2/src/lib.rs","--json=diagnostic-rendered-ansi","--crate-type","lib","--emit=dep-info,metadata","-C","embed-bitcode=no","-C","debuginfo=2","--cfg","feature=\"std\"","-C","metadata=682eda0cbf5d75eb","-C","extra-filename=-682eda0cbf5d75eb","--out-dir","/home/iamkhalifaMBA/Documents/GitHub/storage-adapters/target/rls/debug/deps","-L","dependency=/home/iamkhalifaMBA/Documents/GitHub/storage-adapters/target/rls/debug/deps","--extern","crunchy=/home/iamkhalifaMBA/Documents/GitHub/storage-adapters/target/rls/debug/deps/libcrunchy-4361ff58e1bafe6b.rmeta","--cap-lints","allow","--error-format=json","--sysroot","/home/iamkhalifaMBA/.rustup/toolchains/nightly-2020-11-16-x86_64-unknown-linux-gnu"],"output":"/home/iamkhalifaMBA/Documents/GitHub/storage-adapters/target/rls/debug/deps/libhash256_std_hasher-682eda0cbf5d75eb.rmeta"},"prelude":{"crate_id":{"name":"hash256_std_hasher","disambiguator":[7216271657354883892,14596776321149749660]},"crate_root":"/home/iamkhalifaMBA/.cargo/registry/src/github.com-1ecc6299db9ec823/hash256-std-hasher-0.15.2/src","external_crates":[{"file_name":"/home/iamkhalifaMBA/.cargo/registry/src/github.com-1ecc6299db9ec823/hash256-std-hasher-0.15.2/src/lib.rs","num":1,"id":{"name":"std","disambiguator":[9498309081039753288,17146171879327973561]}},{"file_name":"/home/iamkhalifaMBA/.cargo/registry/src/github.com-1ecc6299db9ec823/hash256-std-hasher-0.15.2/src/lib.rs","num":2,"id":{"name":"core","disambiguator":[6613225743082300914,1742833353142201501]}},{"file_name":"/home/iamkhalifaMBA/.cargo/registry/src/github.com-1ecc6299db9ec823/hash256-std-hasher-0.15.2/src/lib.rs","num":3,"id":{"name":"compiler_builtins","disambiguator":[11184320297803335556,13858837857589462231]}},{"file_name":"/home/iamkhalifaMBA/.cargo/registry/src/github.com-1ecc6299db9ec823/hash256-std-hasher-0.15.2/src/lib.rs","num":4,"id":{"name":"rustc_std_workspace_core","disambiguator":[7052056008796586215,10378193753915807487]}},{"file_name":"/home/iamkhalifaMBA/.cargo/registry/src/github.com-1ecc6299db9ec823/hash256-std-hasher-0.15.2/src/lib.rs","num":5,"id":{"name":"alloc","disambiguator":[8506919001764560201,14392486609026958309]}},{"file_name":"/home/iamkhalifaMBA/.cargo/registry/src/github.com-1ecc6299db9ec823/hash256-std-hasher-0.15.2/src/lib.rs","num":6,"id":{"name":"libc","disambiguator":[1008138081647881344,7429076406658465872]}},{"file_name":"/home/iamkhalifaMBA/.cargo/registry/src/github.com-1ecc6299db9ec823/hash256-std-hasher-0.15.2/src/lib.rs","num":7,"id":{"name":"unwind","disambiguator":[18264666156363143077,9460446616166571952]}},{"file_name":"/home/iamkhalifaMBA/.cargo/registry/src/github.com-1ecc6299db9ec823/hash256-std-hasher-0.15.2/src/lib.rs","num":8,"id":{"name":"cfg_if","disambiguator":[17775355873057806890,2808787496394745820]}},{"file_name":"/home/iamkhalifaMBA/.cargo/registry/src/github.com-1ecc6299db9ec823/hash256-std-hasher-0.15.2/src/lib.rs","num":9,"id":{"name":"hashbrown","disambiguator":[8284212792698810014,4529520408597658105]}},{"file_name":"/home/iamkhalifaMBA/.cargo/registry/src/github.com-1ecc6299db9ec823/hash256-std-hasher-0.15.2/src/lib.rs","num":10,"id":{"name":"rustc_std_workspace_alloc","disambiguator":[13548000852589409421,10665128085775411653]}},{"file_name":"/home/iamkhalifaMBA/.cargo/registry/src/github.com-1ecc6299db9ec823/hash256-std-hasher-0.15.2/src/lib.rs","num":11,"id":{"name":"rustc_demangle","disambiguator":[16403156102386502054,14681479186798415575]}},{"file_name":"/home/iamkhalifaMBA/.cargo/registry/src/github.com-1ecc6299db9ec823/hash256-std-hasher-0.15.2/src/lib.rs","num":12,"id":{"name":"addr2line","disambiguator":[4744697088543495219,7482183864854537400]}},{"file_name":"/home/iamkhalifaMBA/.cargo/registry/src/github.com-1ecc6299db9ec823/hash256-std-hasher-0.15.2/src/lib.rs","num":13,"id":{"name":"gimli","disambiguator":[14313419318706340198,11848972895184007450]}},{"file_name":"/home/iamkhalifaMBA/.cargo/registry/src/github.com-1ecc6299db9ec823/hash256-std-hasher-0.15.2/src/lib.rs","num":14,"id":{"name":"object","disambiguator":[348214952294252407,14922950223543918643]}},{"file_name":"/home/iamkhalifaMBA/.cargo/registry/src/github.com-1ecc6299db9ec823/hash256-std-hasher-0.15.2/src/lib.rs","num":15,"id":{"name":"miniz_oxide","disambiguator":[16253973858345478383,14509903005583630510]}},{"file_name":"/home/iamkhalifaMBA/.cargo/registry/src/github.com-1ecc6299db9ec823/hash256-std-hasher-0.15.2/src/lib.rs","num":16,"id":{"name":"adler","disambiguator":[2318734762227737502,9918336217617466618]}},{"file_name":"/home/iamkhalifaMBA/.cargo/registry/src/github.com-1ecc6299db9ec823/hash256-std-hasher-0.15.2/src/lib.rs","num":17,"id":{"name":"panic_unwind","disambiguator":[14919014723969444451,7741459782339596399]}},{"file_name":"/home/iamkhalifaMBA/.cargo/registry/src/github.com-1ecc6299db9ec823/hash256-std-hasher-0.15.2/src/lib.rs","num":18,"id":{"name":"crunchy","disambiguator":[7753236336316964915,14681294473272407427]}}],"span":{"file_name":"/home/iamkhalifaMBA/.cargo/registry/src/github.com-1ecc6299db9ec823/hash256-std-hasher-0.15.2/src/lib.rs","byte_start":603,"byte_end":1945,"line_start":15,"line_end":75,"column_start":1,"column_end":2}},"imports":[],"defs":[{"kind":"Mod","id":{"krate":0,"index":0},"span":{"file_name":"/home/iamkhalifaMBA/.cargo/registry/src/github.com-1ecc6299db9ec823/hash256-std-hasher-0.15.2/src/lib.rs","byte_start":603,"byte_end":1945,"line_start":15,"line_end":75,"column_start":1,"column_end":2},"name":"","qualname":"::","value":"/home/iamkhalifaMBA/.cargo/registry/src/github.com-1ecc6299db9ec823/hash256-std-hasher-0.15.2/src/lib.rs","parent":null,"children":[{"krate":0,"index":1},{"krate":0,"index":2},{"krate":0,"index":3},{"krate":0,"index":4},{"krate":0,"index":8},{"krate":0,"index":10},{"krate":0,"index":5}],"decl_id":null,"docs":"","sig":null,"attributes":[]},{"kind":"Struct","id":{"krate":0,"index":8},"span":{"file_name":"/home/iamkhalifaMBA/.cargo/registry/src/github.com-1ecc6299db9ec823/hash256-std-hasher-0.15.2/src/lib.rs","byte_start":907,"byte_end":923,"line_start":29,"line_end":29,"column_start":12,"column_end":28},"name":"Hash256StdHasher","qualname":"::Hash256StdHasher","value":"Hash256StdHasher {  }","parent":null,"children":[{"krate":0,"index":9}],"decl_id":null,"docs":" Hasher that just takes 8 bytes of the provided value.\n May only be used for keys which are 32 bytes.\n","sig":null,"attributes":[{"value":"/ Hasher that just takes 8 bytes of the provided value.","span":{"file_name":"/home/iamkhalifaMBA/.cargo/registry/src/github.com-1ecc6299db9ec823/hash256-std-hasher-0.15.2/src/lib.rs","byte_start":769,"byte_end":826,"line_start":26,"line_end":26,"column_start":1,"column_end":58}},{"value":"/ May only be used for keys which are 32 bytes.","span":{"file_name":"/home/iamkhalifaMBA/.cargo/registry/src/github.com-1ecc6299db9ec823/hash256-std-hasher-0.15.2/src/lib.rs","byte_start":827,"byte_end":876,"line_start":27,"line_end":27,"column_start":1,"column_end":50}}]}],"impls":[{"id":0,"kind":"Direct","span":{"file_name":"/home/iamkhalifaMBA/.cargo/registry/src/github.com-1ecc6299db9ec823/hash256-std-hasher-0.15.2/src/lib.rs","byte_start":965,"byte_end":981,"line_start":33,"line_end":33,"column_start":23,"column_end":39},"value":"","parent":null,"children":[{"krate":0,"index":6},{"krate":0,"index":7}],"docs":"","sig":null,"attributes":[]}],"refs":[],"macro_refs":[],"relations":[{"span":{"file_name":"/home/iamkhalifaMBA/.cargo/registry/src/github.com-1ecc6299db9ec823/hash256-std-hasher-0.15.2/src/lib.rs","byte_start":965,"byte_end":981,"line_start":33,"line_end":33,"column_start":23,"column_end":39},"kind":{"Impl":{"id":0}},"from":{"krate":0,"index":8},"to":{"krate":2,"index":6795}}]}